[{"t":1557115500,"o":0.05,"h":0.05,"l":0.05,"c":0.05,"v":0,"strike":11800,"spot":11619.2,"synthetic":true},{"t":1557115800,"o":0.05,"h":0.05,"l":0.05,"c":0.05,"v":0,"strike":11800,"spot":11628.5,"synthetic":true},{"t":1557116100,"o":0.05,"h":0.05,"l":0.05,"c":0.05,"v":0,"strike":11800,"spot":11619.1,"synthetic":true},{"t":1557116400,"o":0.05,"h":0.05,"l":0.05,"c":0.05,"v":0,"strike":11800,"spot":11623.1,"synthetic":true},{"t":1557116700,"o":0.05,"h":0.05,"l":0.05,"c":0.05,"v":0,"strike":11800,"spot":11624,"synthetic":true},{"t":1557117000,"o":0.05,"h":0.05,"l":0.05,"c":0.05,"v":0,"strike":11800,"spot":11620.6,"synthetic":true},{"t":1557117300,"o":0.05,"h":0.05,"l":0.05,"c":0.05,"v":0,"strike":11800,"spot":11616.3999,"synthetic":true},{"t":1557117600,"o":0.05,"h":0.05,"l":0.05,"c":0.05,"v":0,"strike":11800,"spot":11617.7,"synthetic":true},{"t":1557117900,"o":0.05,"h":0.05,"l":0.05,"c":0.05,"v":0,"strike":11800,"spot":11612.6,"synthetic":true},{"t":1557118200,"o":0.05,"h":0.05,"l":0.05,"c":0.05,"v":0,"strike":11800,"spot":11613.2,"synthetic":true},{"t":1557118500,"o":0.05,"h":0.05,"l":0.05,"c":0.05,"v":0,"strike":11800,"spot":11623.1,"synthetic":true},{"t":1557118800,"o":0.05,"h":0.05,"l":0.05,"c":0.05,"v":0,"strike":11800,"spot":11626,"synthetic":true},{"t":1557119100,"o":0.05,"h":0.05,"l":0.05,"c":0.05,"v":0,"strike":11800,"spot":11626.1,"synthetic":true},{"t":1557119400,"o":0.05,"h":0.05,"l":0.05,"c":0.05,"v":0,"strike":11800,"spot":11625.2999,"synthetic":true},{"t":1557119700,"o":0.05,"h":0.05,"l":0.05,"c":0.05,"v":0,"strike":11800,"spot":11618.1,"synthetic":true},{"t":1557120000,"o":0.05,"h":0.05,"l":0.05,"c":0.05,"v":0,"strike":11800,"spot":11623.8999,"synthetic":true},{"t":1557120300,"o":0.05,"h":0.05,"l":0.05,"c":0.05,"v":0,"strike":11800,"spot":11621.6,"synthetic":true},{"t":1557120600,"o":0.05,"h":0.05,"l":0.05,"c":0.05,"v":0,"strike":11800,"spot":11613.5,"synthetic":true},{"t":1557120900,"o":0.05,"h":0.05,"l":0.05,"c":0.05,"v":0,"strike":11800,"spot":11615.5,"synthetic":true},{"t":1557121200,"o":0.05,"h":0.05,"l":0.05,"c":0.05,"v":0,"strike":11800,"spot":11618.6,"synthetic":true},{"t":1557121500,"o":0.05,"h":0.05,"l":0.05,"c":0.05,"v":0,"strike":11800,"spot":11618.6,"synthetic":true},{"t":1557121800,"o":0.05,"h":0.05,"l":0.05,"c":0.05,"v":0,"strike":11800,"spot":11617.2,"synthetic":true},{"t":1557122100,"o":0.05,"h":0.05,"l":0.05,"c":0.05,"v":0,"strike":11800,"spot":11611.7999,"synthetic":true},{"t":1557122400,"o":0.05,"h":0.05,"l":0.05,"c":0.05,"v":0,"strike":11800,"spot":11614.2999,"synthetic":true},{"t":1557122700,"o":0.05,"h":0.05,"l":0.05,"c":0.05,"v":0,"strike":11800,"spot":11616,"synthetic":true},{"t":1557123000,"o":0.05,"h":0.05,"l":0.05,"c":0.05,"v":0,"strike":11800,"spot":11616.2999,"synthetic":true},{"t":1557123300,"o":0.05,"h":0.05,"l":0.05,"c":0.05,"v":0,"strike":11800,"spot":11617.6,"synthetic":true},{"t":1557123600,"o":0.05,"h":0.05,"l":0.05,"c":0.05,"v":0,"strike":11800,"spot":11619.6,"synthetic":true},{"t":1557123900,"o":0.05,"h":0.05,"l":0.05,"c":0.05,"v":0,"strike":11800,"spot":11616.1,"synthetic":true},{"t":1557124200,"o":0.05,"h":0.05,"l":0.05,"c":0.05,"v":0,"strike":11800,"spot":11614.3999,"synthetic":true},{"t":1557124500,"o":0.05,"h":0.05,"l":0.05,"c":0.05,"v":0,"strike":11800,"spot":11615.5,"synthetic":true},{"t":1557124800,"o":0.05,"h":0.05,"l":0.05,"c":0.05,"v":0,"strike":11800,"spot":11615.2,"synthetic":true},{"t":1557125100,"o":0.05,"h":0.05,"l":0.05,"c":0.05,"v":0,"strike":11800,"spot":11623.6,"synthetic":true},{"t":1557125400,"o":0.05,"h":0.05,"l":0.05,"c":0.05,"v":0,"strike":11800,"spot":11626,"synthetic":true},{"t":1557125700,"o":0.05,"h":0.05,"l":0.05,"c":0.05,"v":0,"strike":11800,"spot":11617.5,"synthetic":true},{"t":1557126000,"o":0.05,"h":0.05,"l":0.05,"c":0.05,"v":0,"strike":11800,"spot":11618.5,"synthetic":true},{"t":1557126300,"o":0.05,"h":0.05,"l":0.05,"c":0.05,"v":0,"strike":11800,"spot":11616.3999,"synthetic":true},{"t":1557126600,"o":0.05,"h":0.05,"l":0.05,"c":0.05,"v":0,"strike":11800,"spot":11617.6,"synthetic":true},{"t":1557126900,"o":0.05,"h":0.05,"l":0.05,"c":0.05,"v":0,"strike":11800,"spot":11621,"synthetic":true},{"t":1557127200,"o":0.05,"h":0.05,"l":0.05,"c":0.05,"v":0,"strike":11800,"spot":11625.8999,"synthetic":true},{"t":1557127500,"o":0.05,"h":0.05,"l":0.05,"c":0.05,"v":0,"strike":11800,"spot":11617.8999,"synthetic":true},{"t":1557127800,"o":0.05,"h":0.05,"l":0.05,"c":0.05,"v":0,"strike":11800,"spot":11619.2,"synthetic":true},{"t":1557128100,"o":0.05,"h":0.05,"l":0.05,"c":0.05,"v":0,"strike":11800,"spot":11615.7,"synthetic":true},{"t":1557128400,"o":0.05,"h":0.05,"l":0.05,"c":0.05,"v":0,"strike":11800,"spot":11601.3999,"synthetic":true},{"t":1557128700,"o":0.05,"h":0.05,"l":0.05,"c":0.05,"v":0,"strike":11800,"spot":11600.8999,"synthetic":true},{"t":1557129000,"o":0.05,"h":0.05,"l":0.05,"c":0.05,"v":0,"strike":11800,"spot":11600,"synthetic":true},{"t":1557129300,"o":0.05,"h":0.05,"l":0.05,"c":0.05,"v":0,"strike":11800,"spot":11603.5,"synthetic":true},{"t":1557129600,"o":0.05,"h":0.05,"l":0.05,"c":0.05,"v":0,"strike":11800,"spot":11603.2,"synthetic":true},{"t":1557129900,"o":0.05,"h":0.05,"l":0.05,"c":0.05,"v":0,"strike":11800,"spot":11596.7999,"synthetic":true},{"t":1557130200,"o":0.05,"h":0.05,"l":0.05,"c":0.05,"v":0,"strike":11800,"spot":11597.5,"synthetic":true},{"t":1557130500,"o":0.05,"h":0.05,"l":0.05,"c":0.05,"v":0,"strike":11800,"spot":11601.7999,"synthetic":true},{"t":1557130800,"o":0.05,"h":0.05,"l":0.05,"c":0.05,"v":0,"strike":11800,"spot":11596.2999,"synthetic":true},{"t":1557131100,"o":0.05,"h":0.05,"l":0.05,"c":0.05,"v":0,"strike":11800,"spot":11596.2999,"synthetic":true},{"t":1557131400,"o":0.05,"h":0.05,"l":0.05,"c":0.05,"v":0,"strike":11800,"spot":11596.3999,"synthetic":true},{"t":1557131700,"o":0.05,"h":0.05,"l":0.05,"c":0.05,"v":0,"strike":11800,"spot":11601.2999,"synthetic":true},{"t":1557132000,"o":0.05,"h":0.05,"l":0.05,"c":0.05,"v":0,"strike":11800,"spot":11605.2999,"synthetic":true},{"t":1557132300,"o":0.05,"h":0.05,"l":0.05,"c":0.05,"v":0,"strike":11800,"spot":11603.5,"synthetic":true},{"t":1557132600,"o":0.05,"h":0.05,"l":0.05,"c":0.05,"v":0,"strike":11800,"spot":11600.1,"synthetic":true},{"t":1557132900,"o":0.05,"h":0.05,"l":0.05,"c":0.05,"v":0,"strike":11800,"spot":11600.7999,"synthetic":true},{"t":1557133200,"o":0.05,"h":0.05,"l":0.05,"c":0.05,"v":0,"strike":11800,"spot":11582.6,"synthetic":true},{"t":1557133500,"o":0.05,"h":0.05,"l":0.05,"c":0.05,"v":0,"strike":11800,"spot":11582.3999,"synthetic":true},{"t":1557133800,"o":0.05,"h":0.05,"l":0.05,"c":0.05,"v":0,"strike":11800,"spot":11585,"synthetic":true},{"t":1557134100,"o":0.05,"h":0.05,"l":0.05,"c":0.05,"v":0,"strike":11800,"spot":11581.5,"synthetic":true},{"t":1557134400,"o":0.05,"h":0.05,"l":0.05,"c":0.05,"v":0,"strike":11800,"spot":11576.7,"synthetic":true},{"t":1557134700,"o":0.05,"h":0.05,"l":0.05,"c":0.05,"v":0,"strike":11800,"spot":11586.5,"synthetic":true},{"t":1557135000,"o":0.05,"h":0.05,"l":0.05,"c":0.05,"v":0,"strike":11800,"spot":11607.6,"synthetic":true},{"t":1557135300,"o":0.05,"h":0.05,"l":0.05,"c":0.05,"v":0,"strike":11800,"spot":11597.2999,"synthetic":true},{"t":1557135600,"o":0.05,"h":0.05,"l":0.05,"c":0.05,"v":0,"strike":11800,"spot":11596.8999,"synthetic":true},{"t":1557135900,"o":0.05,"h":0.05,"l":0.05,"c":0.05,"v":0,"strike":11800,"spot":11599.8999,"synthetic":true},{"t":1557136200,"o":0.05,"h":0.05,"l":0.05,"c":0.05,"v":0,"strike":11800,"spot":11598.7,"synthetic":true},{"t":1557136500,"o":0.05,"h":0.05,"l":0.05,"c":0.05,"v":0,"strike":11800,"spot":11592.7999,"synthetic":true}]