[{"t":1526875500,"o":0.05,"h":0.05,"l":0.05,"c":0.05,"v":0,"strike":10400,"spot":10617,"synthetic":true},{"t":1526875800,"o":0.05,"h":0.05,"l":0.05,"c":0.05,"v":0,"strike":10400,"spot":10613.5,"synthetic":true},{"t":1526876100,"o":0.05,"h":0.05,"l":0.05,"c":0.05,"v":0,"strike":10400,"spot":10608,"synthetic":true},{"t":1526876400,"o":0.05,"h":0.05,"l":0.05,"c":0.05,"v":0,"strike":10400,"spot":10603.2,"synthetic":true},{"t":1526876700,"o":0.05,"h":0.05,"l":0.05,"c":0.05,"v":0,"strike":10400,"spot":10593.2,"synthetic":true},{"t":1526877000,"o":0.05,"h":0.05,"l":0.05,"c":0.05,"v":0,"strike":10400,"spot":10586.2,"synthetic":true},{"t":1526877300,"o":0.05,"h":0.05,"l":0.05,"c":0.05,"v":0,"strike":10400,"spot":10582.7,"synthetic":true},{"t":1526877600,"o":0.05,"h":0.05,"l":0.05,"c":0.05,"v":0,"strike":10400,"spot":10576.3999,"synthetic":true},{"t":1526877900,"o":0.05,"h":0.05,"l":0.05,"c":0.05,"v":0,"strike":10400,"spot":10577.1,"synthetic":true},{"t":1526878200,"o":0.05,"h":0.05,"l":0.05,"c":0.05,"v":0,"strike":10400,"spot":10588,"synthetic":true},{"t":1526878500,"o":0.05,"h":0.05,"l":0.05,"c":0.05,"v":0,"strike":10400,"spot":10577.5,"synthetic":true},{"t":1526878800,"o":0.05,"h":0.05,"l":0.05,"c":0.05,"v":0,"strike":10400,"spot":10561.2,"synthetic":true},{"t":1526879100,"o":0.05,"h":0.05,"l":0.05,"c":0.05,"v":0,"strike":10400,"spot":10564.7,"synthetic":true},{"t":1526879400,"o":0.05,"h":0.05,"l":0.05,"c":0.05,"v":0,"strike":10400,"spot":10567.7,"synthetic":true},{"t":1526879700,"o":0.05,"h":0.05,"l":0.05,"c":0.05,"v":0,"strike":10400,"spot":10566.7999,"synthetic":true},{"t":1526880000,"o":0.05,"h":0.05,"l":0.05,"c":0.05,"v":0,"strike":10400,"spot":10558.7999,"synthetic":true},{"t":1526880300,"o":0.05,"h":0.05,"l":0.05,"c":0.05,"v":0,"strike":10400,"spot":10555.7999,"synthetic":true},{"t":1526880600,"o":0.05,"h":0.05,"l":0.05,"c":0.05,"v":0,"strike":10400,"spot":10556.8999,"synthetic":true},{"t":1526880900,"o":0.05,"h":0.05,"l":0.05,"c":0.05,"v":0,"strike":10400,"spot":10567.5,"synthetic":true},{"t":1526881200,"o":0.05,"h":0.05,"l":0.05,"c":0.05,"v":0,"strike":10400,"spot":10569.5,"synthetic":true},{"t":1526881500,"o":0.05,"h":0.05,"l":0.05,"c":0.05,"v":0,"strike":10400,"spot":10567.7999,"synthetic":true},{"t":1526881800,"o":0.05,"h":0.05,"l":0.05,"c":0.05,"v":0,"strike":10400,"spot":10566.1,"synthetic":true},{"t":1526882100,"o":0.05,"h":0.05,"l":0.05,"c":0.05,"v":0,"strike":10400,"spot":10563.3999,"synthetic":true},{"t":1526882400,"o":0.05,"h":0.05,"l":0.05,"c":0.05,"v":0,"strike":10400,"spot":10550.2999,"synthetic":true},{"t":1526882700,"o":0.05,"h":0.05,"l":0.05,"c":0.05,"v":0,"strike":10400,"spot":10552.8999,"synthetic":true},{"t":1526883000,"o":0.05,"h":0.05,"l":0.05,"c":0.05,"v":0,"strike":10400,"spot":10550.7,"synthetic":true},{"t":1526883300,"o":0.05,"h":0.05,"l":0.05,"c":0.05,"v":0,"strike":10400,"spot":10546,"synthetic":true},{"t":1526883600,"o":0.05,"h":0.05,"l":0.05,"c":0.05,"v":0,"strike":10400,"spot":10547.1,"synthetic":true},{"t":1526883900,"o":0.05,"h":0.05,"l":0.05,"c":0.05,"v":0,"strike":10400,"spot":10546.7,"synthetic":true},{"t":1526884200,"o":0.05,"h":0.05,"l":0.05,"c":0.05,"v":0,"strike":10400,"spot":10547.5,"synthetic":true},{"t":1526884500,"o":0.05,"h":0.05,"l":0.05,"c":0.05,"v":0,"strike":10400,"spot":10541.2999,"synthetic":true},{"t":1526884800,"o":0.05,"h":0.05,"l":0.05,"c":0.05,"v":0,"strike":10400,"spot":10542.7,"synthetic":true},{"t":1526885100,"o":0.05,"h":0.05,"l":0.05,"c":0.05,"v":0,"strike":10400,"spot":10541.5,"synthetic":true},{"t":1526885400,"o":0.05,"h":0.05,"l":0.05,"c":0.05,"v":0,"strike":10400,"spot":10531.3999,"synthetic":true},{"t":1526885700,"o":0.05,"h":0.05,"l":0.05,"c":0.05,"v":0,"strike":10400,"spot":10535.1,"synthetic":true},{"t":1526886000,"o":0.05,"h":0.05,"l":0.05,"c":0.05,"v":0,"strike":10400,"spot":10543,"synthetic":true},{"t":1526886300,"o":0.05,"h":0.05,"l":0.05,"c":0.05,"v":0,"strike":10400,"spot":10536.6,"synthetic":true},{"t":1526886600,"o":0.05,"h":0.05,"l":0.05,"c":0.05,"v":0,"strike":10400,"spot":10534.6,"synthetic":true},{"t":1526886900,"o":0.05,"h":0.05,"l":0.05,"c":0.05,"v":0,"strike":10400,"spot":10528.2,"synthetic":true},{"t":1526887200,"o":0.05,"h":0.05,"l":0.05,"c":0.05,"v":0,"strike":10400,"spot":10535.6,"synthetic":true},{"t":1526887500,"o":0.05,"h":0.05,"l":0.05,"c":0.05,"v":0,"strike":10400,"spot":10537.2999,"synthetic":true},{"t":1526887800,"o":0.05,"h":0.05,"l":0.05,"c":0.05,"v":0,"strike":10400,"spot":10534.6,"synthetic":true},{"t":1526888100,"o":0.05,"h":0.05,"l":0.05,"c":0.05,"v":0,"strike":10400,"spot":10532.7,"synthetic":true},{"t":1526888400,"o":0.05,"h":0.05,"l":0.05,"c":0.05,"v":0,"strike":10400,"spot":10534.6,"synthetic":true},{"t":1526888700,"o":0.05,"h":0.05,"l":0.05,"c":0.05,"v":0,"strike":10400,"spot":10531,"synthetic":true},{"t":1526889000,"o":0.05,"h":0.05,"l":0.05,"c":0.05,"v":0,"strike":10400,"spot":10525.3999,"synthetic":true},{"t":1526889300,"o":0.05,"h":0.05,"l":0.05,"c":0.05,"v":0,"strike":10400,"spot":10531.5,"synthetic":true},{"t":1526889600,"o":0.05,"h":0.05,"l":0.05,"c":0.05,"v":0,"strike":10400,"spot":10532,"synthetic":true},{"t":1526889900,"o":0.05,"h":0.05,"l":0.05,"c":0.05,"v":0,"strike":10400,"spot":10537.5,"synthetic":true},{"t":1526890200,"o":0.05,"h":0.05,"l":0.05,"c":0.05,"v":0,"strike":10400,"spot":10541.7,"synthetic":true},{"t":1526890500,"o":0.05,"h":0.05,"l":0.05,"c":0.05,"v":0,"strike":10400,"spot":10533.1,"synthetic":true},{"t":1526890800,"o":0.05,"h":0.05,"l":0.05,"c":0.05,"v":0,"strike":10400,"spot":10529.6,"synthetic":true},{"t":1526891100,"o":0.05,"h":0.05,"l":0.05,"c":0.05,"v":0,"strike":10400,"spot":10522.3999,"synthetic":true},{"t":1526891400,"o":0.05,"h":0.05,"l":0.05,"c":0.05,"v":0,"strike":10400,"spot":10521.2999,"synthetic":true},{"t":1526891700,"o":0.05,"h":0.05,"l":0.05,"c":0.05,"v":0,"strike":10400,"spot":10518.7,"synthetic":true},{"t":1526892000,"o":0.05,"h":0.05,"l":0.05,"c":0.05,"v":0,"strike":10400,"spot":10517.6,"synthetic":true},{"t":1526892300,"o":0.05,"h":0.05,"l":0.05,"c":0.05,"v":0,"strike":10400,"spot":10515.2999,"synthetic":true},{"t":1526892600,"o":0.05,"h":0.05,"l":0.05,"c":0.05,"v":0,"strike":10400,"spot":10516.7999,"synthetic":true},{"t":1526892900,"o":0.05,"h":0.05,"l":0.05,"c":0.05,"v":0,"strike":10400,"spot":10508,"synthetic":true},{"t":1526893200,"o":0.05,"h":0.05,"l":0.05,"c":0.05,"v":0,"strike":10400,"spot":10511,"synthetic":true},{"t":1526893500,"o":0.05,"h":0.05,"l":0.05,"c":0.05,"v":0,"strike":10400,"spot":10526.5,"synthetic":true},{"t":1526893800,"o":0.05,"h":0.05,"l":0.05,"c":0.05,"v":0,"strike":10400,"spot":10519.8999,"synthetic":true},{"t":1526894100,"o":0.05,"h":0.05,"l":0.05,"c":0.05,"v":0,"strike":10400,"spot":10515.7,"synthetic":true},{"t":1526894400,"o":0.05,"h":0.05,"l":0.05,"c":0.05,"v":0,"strike":10400,"spot":10522.5,"synthetic":true},{"t":1526894700,"o":0.05,"h":0.05,"l":0.05,"c":0.05,"v":0,"strike":10400,"spot":10523.2,"synthetic":true},{"t":1526895000,"o":0.05,"h":0.05,"l":0.05,"c":0.05,"v":0,"strike":10400,"spot":10515.2,"synthetic":true},{"t":1526895300,"o":0.05,"h":0.05,"l":0.05,"c":0.05,"v":0,"strike":10400,"spot":10514.6,"synthetic":true},{"t":1526895600,"o":0.05,"h":0.05,"l":0.05,"c":0.05,"v":0,"strike":10400,"spot":10520.2,"synthetic":true},{"t":1526895900,"o":0.05,"h":0.05,"l":0.05,"c":0.05,"v":0,"strike":10400,"spot":10515.2,"synthetic":true},{"t":1526896200,"o":0.05,"h":0.05,"l":0.05,"c":0.05,"v":0,"strike":10400,"spot":10514.7999,"synthetic":true},{"t":1526896500,"o":0.05,"h":0.05,"l":0.05,"c":0.05,"v":0,"strike":10400,"spot":10520.7999,"synthetic":true}]